phinet/__init__.py
phinet/model.py
phinet-0.1.dist-info/METADATA
phinet-0.1.dist-info/WHEEL
phinet-0.1.dist-info/top_level.txt
phinet-0.1.dist-info/RECORD
